sqlalchemy_utils_async/__init__.py
sqlalchemy_utils_async/_db.py
sqlalchemy_utils_async/_select.py
sqlalchemy_utils_async/_typings.py
sqlalchemy_utils_async/manager.py
sqlalchemy_utils_async/skeleton.py
sqlalchemy_utils_async-0.1.0.dist-info/entry_points.txt
sqlalchemy_utils_async-0.1.0.dist-info/licenses/LICENSE.txt
sqlalchemy_utils_async-0.1.0.dist-info/WHEEL
sqlalchemy_utils_async-0.1.0.dist-info/METADATA
sqlalchemy_utils_async-0.1.0.dist-info/RECORD
